click_pwsh/__init__.py
click_pwsh/__main__.py
click_pwsh/shell_completion.py
click_pwsh-0.9.5.dist-info/LICENSE
click_pwsh-0.9.5.dist-info/METADATA
click_pwsh-0.9.5.dist-info/WHEEL
click_pwsh-0.9.5.dist-info/RECORD
