Metadata-Version: 2.1
Name: click-pwsh
Version: 0.9.5
Summary: A click extension to support shell completion for PowerShell 7
Home-page: https://github.com/StephLin/click-pwsh
License: BSD-3-Clause
Author: Yu-Kai Lin
Author-email: stephen359595@gmail.com
Requires-Python: >=3.6,<4.0
Classifier: License :: OSI Approved :: BSD License
Classifier: Programming Language :: Python :: 3
Classifier: Programming Language :: Python :: 3.6
Classifier: Programming Language :: Python :: 3.7
Classifier: Programming Language :: Python :: 3.8
Classifier: Programming Language :: Python :: 3.9
Classifier: Programming Language :: Python :: 3.10
Classifier: Programming Language :: Python :: 3.11
Classifier: Programming Language :: Python :: 3.12
Requires-Dist: click (>=8.0.0,<9.0.0)
Project-URL: Repository, https://github.com/StephLin/click-pwsh
